src/__init__.py
src/content_type.json
src/file_signatures.json
src/finder.py
request_content_type_finder-0.1.0.dist-info/LICENSE
request_content_type_finder-0.1.0.dist-info/METADATA
request_content_type_finder-0.1.0.dist-info/WHEEL
request_content_type_finder-0.1.0.dist-info/top_level.txt
request_content_type_finder-0.1.0.dist-info/RECORD
