Metadata-Version: 2.1
Name: request-content-type-finder
Version: 0.1.0
Summary: Finds content type of request response from content disposition/ content type and when content disposition and content type not present in response headers
Home-page: https://github.com/shivamkadukar
Author: Shivam Kadukar
Author-email: shivamk2802@gmail.com
Classifier: Development Status :: 4 - Beta
Classifier: Intended Audience :: Developers
Classifier: Intended Audience :: Science/Research
Classifier: License :: OSI Approved :: MIT License
Classifier: Natural Language :: English
Classifier: Operating System :: OS Independent
Classifier: Programming Language :: Python
Classifier: Programming Language :: Python :: 3
Classifier: Programming Language :: Python :: 3.9
Requires-Python: >=3.9.0
License-File: LICENSE
